pelican/plugins/mdimage/__init__.py
pelican/plugins/mdimage/core.py
pelican_markdown_image-0.1.1.dist-info/LICENSE
pelican_markdown_image-0.1.1.dist-info/METADATA
pelican_markdown_image-0.1.1.dist-info/WHEEL
pelican_markdown_image-0.1.1.dist-info/top_level.txt
pelican_markdown_image-0.1.1.dist-info/RECORD
