Metadata-Version: 2.1
Name: pelican-markdown-image
Version: 0.1.1
Summary: A plugin for pelican to use native markdown image syntax
Home-page: https://github.com/cjc7373/pelican-markdown-image
Author: cjc7373
Author-email: niuchangcun@gmail.com
License: UNKNOWN
Platform: UNKNOWN
Classifier: Programming Language :: Python :: 3
Classifier: License :: OSI Approved :: MIT License
Classifier: Operating System :: OS Independent
Requires-Python: >=3.7
Requires-Dist: beautifulsoup4
